cmoncrawl/__init__.py
cmoncrawl/config.py
cmoncrawl/aggregator/__init__.py
cmoncrawl/aggregator/athena_query.py
cmoncrawl/aggregator/base.py
cmoncrawl/aggregator/gateway_query.py
cmoncrawl/aggregator/.vscode/settings.json
cmoncrawl/aggregator/utils/__init__.py
cmoncrawl/aggregator/utils/athena_query_maker.py
cmoncrawl/aggregator/utils/constants.py
cmoncrawl/aggregator/utils/helpers.py
cmoncrawl/aggregator/utils/ndjson.py
cmoncrawl/common/__init__.py
cmoncrawl/common/caching.py
cmoncrawl/common/loggers.py
cmoncrawl/common/throttling.py
cmoncrawl/common/types.py
cmoncrawl/integrations/__init__.py
cmoncrawl/integrations/commands.py
cmoncrawl/integrations/download.py
cmoncrawl/integrations/extract.py
cmoncrawl/integrations/utils.py
cmoncrawl/middleware/__init__.py
cmoncrawl/middleware/stompware.py
cmoncrawl/middleware/synchronized.py
cmoncrawl/processor/__init__.py
cmoncrawl/processor/dao/__init__.py
cmoncrawl/processor/dao/api.py
cmoncrawl/processor/dao/base.py
cmoncrawl/processor/dao/s3.py
cmoncrawl/processor/extraction/__init__.py
cmoncrawl/processor/extraction/filters.py
cmoncrawl/processor/extraction/utils.py
cmoncrawl/processor/pipeline/__init__.py
cmoncrawl/processor/pipeline/downloader.py
cmoncrawl/processor/pipeline/extractor.py
cmoncrawl/processor/pipeline/pipeline.py
cmoncrawl/processor/pipeline/router.py
cmoncrawl/processor/pipeline/streamer.py
CmonCrawl-1.1.8.dist-info/LICENSE
CmonCrawl-1.1.8.dist-info/METADATA
CmonCrawl-1.1.8.dist-info/WHEEL
CmonCrawl-1.1.8.dist-info/entry_points.txt
CmonCrawl-1.1.8.dist-info/top_level.txt
CmonCrawl-1.1.8.dist-info/RECORD
