Metadata-Version: 2.1
Name: CmonCrawl
Version: 1.1.8
License: MIT License
Project-URL: Source, https://github.com/hynky1999/CmonCrawl
Keywords: Common Crawl,Crawl,Extractor,Common Crawl Extractor,Web Crawler,Web Extractor,Web Scraper
Classifier: Development Status :: 3 - Alpha
Classifier: License :: OSI Approved :: MIT License
Classifier: Programming Language :: Python :: 3
Classifier: Programming Language :: Python :: 3.11
License-File: LICENSE
Requires-Dist: aiofiles ~=23.2.1
Requires-Dist: aiohttp ~=3.9.3
Requires-Dist: beautifulsoup4 ~=4.12.3
Requires-Dist: pydantic ~=2.6.4
Requires-Dist: stomp.py ~=8.1.0
Requires-Dist: tqdm ~=4.66.1
Requires-Dist: warcio ~=1.7.4
Requires-Dist: aiocsv ~=1.3.1
Requires-Dist: aioboto3 ~=12.3.0
Requires-Dist: tenacity ~=8.2.3
Requires-Dist: python-dotenv ==1.0.0
